LICENSE
MANIFEST.in
README.rst
setup.py
glossolalia/__init__.py
glossolalia/__main__.py
glossolalia/core.py
glossolalia.egg-info/PKG-INFO
glossolalia.egg-info/SOURCES.txt
glossolalia.egg-info/dependency_links.txt
glossolalia.egg-info/entry_points.txt
glossolalia.egg-info/not-zip-safe
glossolalia.egg-info/requires.txt
glossolalia.egg-info/top_level.txt
glossolalia/pseudo/__init__.py
glossolalia/pseudo/splitters.py
glossolalia/pseudo/types.py