Metadata-Version: 1.1
Name: glossolalia
Version: 1.0.0
Summary: Translation Utility to Create Pseudo Translations of PO Files
Home-page: https://github.com/fusionbox/glossolalia
Author: Fusionbox
Author-email: programmers@fusionbox.com
License:             GNU GENERAL PUBLIC LICENSE
